guesslex/__init__.py
guesslex/cli.py
guesslex/core.py
guesslex/model.joblib
guesslex-1.0.2.dist-info/licenses/LICENSE
guesslex-1.0.2.dist-info/METADATA
guesslex-1.0.2.dist-info/WHEEL
guesslex-1.0.2.dist-info/entry_points.txt
guesslex-1.0.2.dist-info/top_level.txt
guesslex-1.0.2.dist-info/RECORD
