Metadata-Version: 2.4
Name: guesslex
Version: 1.0.2
Summary: A machine learning-based programming language detection library
Author-email: Sid Padmanabhuni <siddharth.padm@gmail.com>
Maintainer-email: Sid Padmanabhuni <siddharth.padm@gmail.com>
License: MIT
Project-URL: Repository, https://github.com/SidPad03/guesslex
Project-URL: Issues, https://github.com/SidPad03/guesslex/issues
Keywords: machine-learning,nlp,programming-languages,code-analysis,text-classification
Classifier: Development Status :: 5 - Production/Stable
Classifier: Intended Audience :: Developers
Classifier: Topic :: Software Development :: Libraries :: Python Modules
Classifier: Topic :: Text Processing :: Linguistic
Classifier: Topic :: Scientific/Engineering :: Artificial Intelligence
Classifier: License :: OSI Approved :: MIT License
Classifier: Programming Language :: Python :: 3
Classifier: Programming Language :: Python :: 3.8
Classifier: Programming Language :: Python :: 3.9
Classifier: Programming Language :: Python :: 3.10
Classifier: Programming Language :: Python :: 3.11
Classifier: Programming Language :: Python :: 3.12
Requires-Python: >=3.8
License-File: LICENSE
Requires-Dist: numpy>=1.21.0
Requires-Dist: scikit-learn>=1.0.0
Requires-Dist: joblib>=1.0.0
Provides-Extra: dev
Requires-Dist: pytest>=6.0; extra == "dev"
Requires-Dist: pytest-cov; extra == "dev"
Requires-Dist: black; extra == "dev"
Requires-Dist: flake8; extra == "dev"
Requires-Dist: mypy; extra == "dev"
Dynamic: license-file
